src/build-essentials-agile-north/__init__.py
src/build-essentials-agile-north/devutils.py
build_essentails_agile_north-0.0.3.dist-info/METADATA
build_essentails_agile_north-0.0.3.dist-info/WHEEL
build_essentails_agile_north-0.0.3.dist-info/RECORD
